[
    {
        "target": "google.com",
        "latency_ms": 3,
        "packet_loss_pct": 0,
        "jitter_ms": 1.1,
        "status": "Online",
        "timestamp": "2026-07-12T15:55:08.161589"
    },
    {
        "target": "8.8.8.8",
        "latency_ms": 2,
        "packet_loss_pct": 0,
        "jitter_ms": 0.3,
        "status": "Online",
        "timestamp": "2026-07-12T15:55:09.169799"
    },
    {
        "target": "sanook.com",
        "latency_ms": 279,
        "packet_loss_pct": 0,
        "jitter_ms": 10.5,
        "status": "Online",
        "timestamp": "2026-07-12T15:55:11.565902"
    }
]